{"results":[{"gender":"female","name":{"title":"Mrs","first":"Danielle","last":"Hawkins"},"location":{"street":{"number":2156,"name":"West Street"},"city":"Ripon","state":"Oxfordshire","country":"United Kingdom","postcode":"MH28 6UP","coordinates":{"latitude":"14.5489","longitude":"146.4080"},"timezone":{"offset":"-1:00","description":"Azores, Cape Verde Islands"}},"email":"danielle.hawkins@example.com","login":{"uuid":"36563fbb-c986-435a-8a46-1b23ac267bdc","username":"happybutterfly743","password":"county","salt":"LGzntNbP","md5":"0a8f3d529308ed83d25e26c3f2977fad","sha1":"93acbb829ee7043191aaa4a4818db49cb293ee6b","sha256":"06b3f482360a757e7553bac6ef6859f3e709f0d354c58251d7ea7eefaaed9eb2"},"dob":{"date":"1951-08-10T02:39:27.037Z","age":70},"registered":{"date":"2006-03-28T16:04:03.005Z","age":15},"phone":"017684 27572","cell":"0744-687-608","id":{"name":"NINO","value":"WZ 66 53 17 H"},"picture":{"large":"https://randomuser.me/api/portraits/women/64.jpg","medium":"https://randomuser.me/api/portraits/med/women/64.jpg","thumbnail":"https://randomuser.me/api/portraits/thumb/women/64.jpg"},"nat":"GB"}],"info":{"seed":"affda53e8c44d446","results":1,"page":1,"version":"1.3"}}